{"FT:141":{
  "id":"FT:141","value":2174.55,"ask":2175.02,"bid":2174.55,"tid":"FT:141","timestamp":1581415500},"FT:140":{
  "id":"FT:140","value":6462,"ask":6462,"bid":6462,"tid":"FT:140","timestamp":1581043920},"FT:142":{
  "id":"FT:142","value":0.6674,"ask":0.6723,"bid":0.6674,"tid":"FT:142","timestamp":1582531560},"FT:139":{
  "id":"FT:139","value":6474.5,"ask":6476.5,"bid":6474.5,"tid":"FT:139","timestamp":1581043500},"audcad":{
  "id":"audcad","value":0.8553,"ask":0.8561,"bid":0.8553,"tid":1,"timestamp":1585040453},"audchf":{
  "id":"audchf","value":0.57534,"ask":0.57624,"bid":0.57534,"tid":175,"timestamp":1585040451},"audnzd":{
  "id":"audnzd","value":1.019,"ask":1.0202,"bid":1.019,"tid":3,"timestamp":1585040453},"audjpy":{
  "id":"audjpy","value":65.247,"ask":65.327,"bid":65.247,"tid":2,"timestamp":1585040453},"usdsgd":{
  "id":"usdsgd","value":1.44682,"ask":1.44908,"bid":1.44682,"tid":96,"timestamp":1585040444},"eurusd":{
  "id":"eurusd","value":1.08232,"ask":1.08262,"bid":1.08232,"tid":10,"timestamp":1585040454},"gbpusd":{
  "id":"gbpusd","value":1.17518,"ask":1.17558,"bid":1.17518,"tid":15,"timestamp":1585040451},"usdjpy":{
  "id":"usdjpy","value":110.771,"ask":110.801,"bid":110.771,"tid":23,"timestamp":1585040452},"usdchf":{
  "id":"usdchf","value":0.97683,"ask":0.97723,"bid":0.97683,"tid":21,"timestamp":1585040453},"usdcad":{
  "id":"usdcad","value":1.45181,"ask":1.45221,"bid":1.45181,"tid":20,"timestamp":1585040451},"audusd":{
  "id":"audusd","value":0.5891,"ask":0.5895,"bid":0.5891,"tid":4,"timestamp":1585040453},"nzdusd":{
  "id":"nzdusd","value":0.57778,"ask":0.57818,"bid":0.57778,"tid":19,"timestamp":1585040452},"eurgbp":{
  "id":"eurgbp","value":0.92078,"ask":0.92118,"bid":0.92078,"tid":8,"timestamp":1585040452},"eurchf":{
  "id":"eurchf","value":1.05737,"ask":1.05787,"bid":1.05737,"tid":7,"timestamp":1585040451},"eurjpy":{
  "id":"eurjpy","value":119.901,"ask":119.941,"bid":119.901,"tid":9,"timestamp":1585040453},"euraud":{
  "id":"euraud","value":1.83645,"ask":1.83725,"bid":1.83645,"tid":5,"timestamp":1585040453},"eurcad":{
  "id":"eurcad","value":1.57131,"ask":1.57221,"bid":1.57131,"tid":6,"timestamp":1585040453},"gbpaud":{
  "id":"gbpaud","value":1.99403,"ask":1.99503,"bid":1.99403,"tid":11,"timestamp":1585040453},"gbpcad":{
  "id":"gbpcad","value":1.7061,"ask":1.7073,"bid":1.7061,"tid":12,"timestamp":1585040453},"gbpchf":{
  "id":"gbpchf","value":1.14795,"ask":1.14875,"bid":1.14795,"tid":13,"timestamp":1585040452},"gbpjpy":{
  "id":"gbpjpy","value":130.18,"ask":130.25,"bid":130.18,"tid":14,"timestamp":1585040453},"nzdcad":{
  "id":"nzdcad","value":0.83887,"ask":0.83967,"bid":0.83887,"tid":16,"timestamp":1585040450},"nzdchf":{
  "id":"nzdchf","value":0.56421,"ask":0.56521,"bid":0.56421,"tid":17,"timestamp":1585040452},"nzdjpy":{
  "id":"nzdjpy","value":64.004,"ask":64.064,"bid":64.004,"tid":18,"timestamp":1585040453},"usddkk":{
  "id":"usddkk","value":6.89685,"ask":6.89885,"bid":6.89685,"tid":22,"timestamp":1585040453},"usdmxn":{
  "id":"usdmxn","value":24.87302,"ask":24.89802,"bid":24.87302,"tid":24,"timestamp":1585040453},"usdnok":{
  "id":"usdnok","value":11.08513,"ask":11.09013,"bid":11.08513,"tid":25,"timestamp":1585040453},"usdrub":{
  "id":"usdrub","value":78.4484,"ask":78.8484,"bid":78.4484,"tid":90,"timestamp":1585040453},"usdsek":{
  "id":"usdsek","value":10.24752,"ask":10.25252,"bid":10.24752,"tid":26,"timestamp":1585040452},"usdtry":{
  "id":"usdtry","value":6.46823,"ask":6.48823,"bid":6.46823,"tid":99,"timestamp":1585040453},"silver":{
  "id":"silver","value":13.997,"ask":14.067,"bid":13.997,"tid":27,"timestamp":1585040453},"gold":{
  "id":"gold","value":1602.47,"ask":1603.17,"bid":1602.47,"tid":28,"timestamp":1585040442},"_mmm":{
  "id":"_mmm","value":118.42,"ask":118.98,"bid":118.42,"tid":66,"timestamp":1584979199},"_alibaba":{
  "id":"_alibaba","value":177.17,"ask":178.21,"bid":177.17,"tid":9056,"timestamp":1584979199},"_aa":{
  "id":"_aa","value":5.56,"ask":5.72,"bid":5.56,"tid":39,"timestamp":1584979193},"_amzn":{
  "id":"_amzn","value":1907.56,"ask":1912.28,"bid":1907.56,"tid":41,"timestamp":1584979198},"_axp":{
  "id":"_axp","value":69.08,"ask":69.35,"bid":69.08,"tid":42,"timestamp":1584979199},"_aapl":{
  "id":"_aapl","value":225.14,"ask":226.09,"bid":225.14,"tid":40,"timestamp":1584979199},"_t":{
  "id":"_t","value":26.91,"ask":27.01,"bid":26.91,"tid":73,"timestamp":1584979199},"_bac":{
  "id":"_bac","value":18.15,"ask":18.23,"bid":18.15,"tid":44,"timestamp":1584979199},"_ba":{
  "id":"_ba","value":105.55,"ask":106.26,"bid":105.55,"tid":43,"timestamp":1584979199},"_cat":{
  "id":"_cat","value":92.36,"ask":92.97,"bid":92.36,"tid":45,"timestamp":1584979189},"_cvx":{
  "id":"_cvx","value":54.28,"ask":54.56,"bid":54.28,"tid":47,"timestamp":1584979199},"_ko":{
  "id":"_ko","value":37.6,"ask":37.75,"bid":37.6,"tid":63,"timestamp":1584979199},"_csco":{
  "id":"_csco","value":34.72,"ask":34.82,"bid":34.72,"tid":46,"timestamp":1584979199},"_dis":{
  "id":"_dis","value":86.71,"ask":86.77,"bid":86.71,"tid":49,"timestamp":1584979199},"_ebay":{
  "id":"_ebay","value":26.43,"ask":26.58,"bid":26.43,"tid":50,"timestamp":1584979186},"_xom":{
  "id":"_xom","value":31.8,"ask":32.02,"bid":31.8,"tid":78,"timestamp":1584979198},"_fb":{
  "id":"_fb","value":147.91,"ask":148.9,"bid":147.91,"tid":51,"timestamp":1584979199},"_ge":{
  "id":"_ge","value":6.09,"ask":6.25,"bid":6.09,"tid":52,"timestamp":1584979197},"_goog":{
  "id":"_goog","value":1059.39,"ask":1063.59,"bid":1059.39,"tid":53,"timestamp":1584979196},"_ibm":{
  "id":"_ibm","value":95.53,"ask":95.92,"bid":95.53,"tid":58,"timestamp":1584979199},"_hpq":{
  "id":"_hpq","value":13.78,"ask":13.87,"bid":13.78,"tid":57,"timestamp":1584979199},"_intc":{
  "id":"_intc","value":49.77,"ask":49.88,"bid":49.77,"tid":59,"timestamp":1584979199},"_jnj":{
  "id":"_jnj","value":111.91,"ask":112.29,"bid":111.91,"tid":61,"timestamp":1584979199},"_jpm":{
  "id":"_jpm","value":79.38,"ask":79.84,"bid":79.38,"tid":62,"timestamp":1584979199},"_mcd":{
  "id":"_mcd","value":139.31,"ask":139.82,"bid":139.31,"tid":64,"timestamp":1584979199},"_msft":{
  "id":"_msft","value":136.26,"ask":136.49,"bid":136.26,"tid":69,"timestamp":1584979199},"_netflix":{
  "id":"_netflix","value":359.76,"ask":360.52,"bid":359.76,"tid":9051,"timestamp":1584979198},"_pfe":{
  "id":"_pfe","value":28.63,"ask":28.74,"bid":28.63,"tid":70,"timestamp":1584979199},"_pg":{
  "id":"_pg","value":98.8,"ask":99.12,"bid":98.8,"tid":71,"timestamp":1584979199},"_sony":{
  "id":"_sony","value":53.08,"ask":53.34,"bid":53.08,"tid":90001,"timestamp":1584979199},"_yhoo":{
  "id":"_yhoo","value":54.79,"ask":54.79,"bid":54.79,"tid":80,"timestamp":1498237140},"_tesla":{
  "id":"_tesla","value":432.8,"ask":434.98,"bid":432.8,"tid":2001,"timestamp":1584979199},"_vz":{
  "id":"_vz","value":50.71,"ask":50.86,"bid":50.71,"tid":75,"timestamp":1584979199},"_wmt":{
  "id":"_wmt","value":115,"ask":115.25,"bid":115,"tid":76,"timestamp":1584979199},"_bmw":{
  "id":"_bmw","value":42.338,"ask":42.631,"bid":42.338,"tid":90002,"timestamp":1585040452},"ng":{
  "id":"ng","value":1.733,"ask":1.734,"bid":1.733,"tid":84,"timestamp":1585040453},"ta35":{
  "id":"ta35","value":1253.43,"ask":1253.43,"bid":1253.43,"tid":31,"timestamp":1585040443},"tadawul":{
  "id":"tadawul","value":5998.03,"ask":6214.16,"bid":6209.16,"tid":32,"timestamp":1585036799},"btceur":{
  "id":"btceur","value":6129.91,"ask":6177.01,"bid":6129.91,"tid":167,"timestamp":1585040454},"btcusd":{
  "id":"btcusd","value":6635.9,"ask":6685.9,"bid":6635.9,"tid":107,"timestamp":1585040454},"_gazp":{
  "id":"_gazp","value":176.47,"ask":176.86,"bid":176.47,"tid":94,"timestamp":1585040453},"_yndx":{
  "id":"_yndx","value":29.22,"ask":29.36,"bid":29.22,"tid":81,"timestamp":1584979199},"uso":{
  "id":"uso","value":4.85,"ask":4.86,"bid":4.85,"tid":33,"timestamp":1584979096},"uco":{
  "id":"uco","value":2.13,"ask":2.14,"bid":2.13,"tid":34,"timestamp":1584978728},"adobe":{
  "id":"adobe","value":308.26,"ask":309.07,"bid":308.26,"tid":20005,"timestamp":1584979198},"_nike":{
  "id":"_nike","value":63.12,"ask":63.32,"bid":63.12,"tid":90003,"timestamp":1584979199},"ltcusd":{
  "id":"ltcusd","value":38.86,"ask":40.34,"bid":38.86,"tid":109,"timestamp":1585040454},"dshusd":{
  "id":"dshusd","value":67.97,"ask":69.82,"bid":67.97,"tid":113,"timestamp":1585040449},"ethusd":{
  "id":"ethusd","value":137.34,"ask":139.35,"bid":137.34,"tid":108,"timestamp":1585040453},"xrpusd":{
  "id":"xrpusd","value":0.1477,"ask":0.1747,"bid":0.1477,"tid":112,"timestamp":1585040448},"btcusd2":{
  "id":"btcusd2","value":6635.9,"ask":6685.9,"bid":6635.9,"tid":107000,"timestamp":1585040454},"bchusd":{
  "id":"bchusd","value":228.34,"ask":314.5,"bid":228.34,"tid":110,"timestamp":1542289938},"etcusd":{
  "id":"etcusd","value":4.71,"ask":5.37,"bid":4.71,"tid":119,"timestamp":1585040418},"_lm":{
  "id":"_lm","value":281.42,"ask":282.6,"bid":281.42,"tid":190,"timestamp":1584979199},"_nvidia":{
  "id":"_nvidia","value":212.3,"ask":213.69,"bid":212.3,"tid":9055,"timestamp":1584979199},"bcheur":{
  "id":"bcheur","value":30.11,"ask":277.03,"bid":30.11,"tid":171,"timestamp":1542342200},"etheur":{
  "id":"etheur","value":126.87,"ask":128.74,"bid":126.87,"tid":172,"timestamp":1585040453},"ton2":{
  "id":"ton2","value":4.01,"ask":4.57,"bid":4.01,"tid":20004,"timestamp":1585040453},"dsheur":{
  "id":"dsheur","value":62.77,"ask":64.53,"bid":62.77,"tid":174,"timestamp":1585040449},"_pm":"id"{
  "id":"_pm","value":60.24,"ask":60.56,"bid":60.24,"tid":72,"timestamp":1584979198},"btgusd":{
  "id":"btgusd","value":7.32,"ask":7.78,"bid":7.32,"tid":117,"timestamp":1585040445},"_lkoh":{
  "id":"_lkoh","value":4479.5,"ask":4482,"bid":4479.5,"tid":93,"timestamp":1585040448},"_rosn":{
  "id":"_rosn","value":408.05,"ask":408.1,"bid":408.05,"tid":95,"timestamp":1560515397},"xmrusd":{
  "id":"xmrusd","value":45.28,"ask":45.4,"bid":45.28,"tid":114,"timestamp":1585040452},"xvgusd":{
  "id":"xvgusd","value":0.00242,"ask":0.00253,"bid":0.00242,"tid":138,"timestamp":1585040449},"xemusd":{
  "id":"xemusd","value":0.03915,"ask":0.03958,"bid":0.03915,"tid":135,"timestamp":1585040454},"qtmusd":{
  "id":"qtmusd","value":1.2508,"ask":1.2656,"bid":1.2508,"tid":128,"timestamp":1585040449},"gntusd":{
  "id":"gntusd","value":0.03424,"ask":0.03476,"bid":0.03424,"tid":120,"timestamp":1585040453},"trxusd":{
  "id":"trxusd","value":0.01134,"ask":0.01139,"bid":0.01134,"tid":118,"timestamp":1585040450},"bist100":{
  "id":"bist100","value":88408.62,"ask":88678.64,"bid":88408.62,"tid":35,"timestamp":1585040453},"_baidu":{
  "id":"_baidu","value":91.14,"ask":91.77,"bid":91.14,"tid":1751,"timestamp":1584979198},"eursgd":{
  "id":"eursgd","value":1.56717,"ask":1.56763,"bid":1.56717,"tid":97,"timestamp":1585040454},"eurex":{
  "id":"eurex","value":2549.13,"ask":2551.88,"bid":2549.13,"tid":9042,"timestamp":1585040449},"_uber":{
  "id":"_uber","value":22.46,"ask":22.47,"bid":22.46,"tid":9052,"timestamp":1584979195},"pepsico":{
  "id":"pepsico","value":105.46,"ask":105.58,"bid":105.46,"tid":20006,"timestamp":1584979199},"zs":{
  "id":"zs","value":873.25,"ask":873.75,"bid":873.25,"tid":86,"timestamp":1585039491},"ct":{
  "id":"ct","value":52.99,"ask":53.04,"bid":52.99,"tid":89,"timestamp":1585040441},"zc":{
  "id":"zc","value":339.75,"ask":340,"bid":339.75,"tid":85,"timestamp":1585039499},"nikkei":{
  "id":"nikkei","value":19155,"ask":19168.57,"bid":19155,"tid":36,"timestamp":1585040451},"nasdaq":{
  "id":"nasdaq","value":7332.39,"ask":7333.99,"bid":7332.39,"tid":37,"timestamp":1585040453},"dow":{
  "id":"dow","value":19427,"ask":19450,"bid":19427,"tid":38,"timestamp":1585040381},"sp500":{
  "id":"sp500","value":2330.17,"ask":2330.42,"bid":2330.17,"tid":9038,"timestamp":1585040453},"dax":{
  "id":"dax","value":9255.5,"ask":9257.5,"bid":9255.5,"tid":9039,"timestamp":1585040451},"ftse":{
  "id":"ftse","value":5148,"ask":5149,"bid":5148,"tid":9040,"timestamp":1585040453},"mib":{
  "id":"mib","value":16135,"ask":16145,"bid":16135,"tid":9041,"timestamp":1585040451},"asx":{
  "id":"asx","value":4820,"ask":4824,"bid":4820,"tid":9043,"timestamp":1585040434},"volsp500":{
  "id":"volsp500","value":43.55,"ask":43.65,"bid":43.55,"tid":9045,"timestamp":1585040441},"jse":{
  "id":"jse","value":37258.07,"ask":37365.57,"bid":37258.07,"tid":9048,"timestamp":1585040449},"iceusd":{
  "id":"iceusd","value":101.975,"ask":101.99,"bid":101.975,"tid":9044,"timestamp":1585040452},"kc":{
  "id":"kc","value":124.51,"ask":124.6,"bid":124.51,"tid":87,"timestamp":1585040448},"sb":{
  "id":"sb","value":881.75,"ask":883.25,"bid":881.75,"tid":88,"timestamp":1583507691},"cac40":{
  "id":"cac40","value":4085,"ask":4086.5,"bid":4085,"tid":9046,"timestamp":1585040449},"ibex":{
  "id":"ibex","value":6440,"ask":6445,"bid":6440,"tid":9047,"timestamp":1585040453},"hshares":{
  "id":"hshares","value":9325,"ask":9380,"bid":9325,"tid":9049,"timestamp":1585040285},"hang_seng":{
  "id":"hang_seng","value":22912,"ask":22950,"bid":22912,"tid":9050,"timestamp":1585040449},"brent":{
  "id":"brent","value":30.22,"ask":30.23,"bid":30.22,"tid":29,"timestamp":1585040448},"wti":{
  "id":"wti","value":24.16,"ask":24.17,"bid":24.16,"tid":30,"timestamp":1585040448}}